spaceone/__init__.py
spaceone/supervisor/__init__.py
spaceone/supervisor/api/__init__.py
spaceone/supervisor/api/v1/__init__.py
spaceone/supervisor/conf/__init__.py
spaceone/supervisor/conf/global_conf.py
spaceone/supervisor/conf/proto_conf.py
spaceone/supervisor/conf/scheduler_conf.py
spaceone/supervisor/connector/__init__.py
spaceone/supervisor/connector/container_connector.py
spaceone/supervisor/connector/docker_connector.py
spaceone/supervisor/connector/kubernetes_connector.py
spaceone/supervisor/connector/plugin_connector.py
spaceone/supervisor/connector/repository_connector.py
spaceone/supervisor/error/__init__.py
spaceone/supervisor/error/supervisor.py
spaceone/supervisor/info/__init__.py
spaceone/supervisor/info/common_info.py
spaceone/supervisor/info/plugin_manager_info.py
spaceone/supervisor/manager/__init__.py
spaceone/supervisor/manager/plugin_service_manager.py
spaceone/supervisor/manager/supervisor_manager.py
spaceone/supervisor/scheduler/__init__.py
spaceone/supervisor/scheduler/sync_scheduler.py
spaceone/supervisor/service/__init__.py
spaceone/supervisor/service/supervisor_service.py
spaceone_supervisor-1.12.0.dist-info/METADATA
spaceone_supervisor-1.12.0.dist-info/WHEEL
spaceone_supervisor-1.12.0.dist-info/top_level.txt
spaceone_supervisor-1.12.0.dist-info/RECORD
