Metadata-Version: 2.1
Name: spaceone-supervisor
Version: 1.12.0
Summary: SpaceONE supervisor service
Home-page: https://www.spaceone.dev/
Author: MEGAZONE SpaceONE Team
Author-email: admin@spaceone.dev
License: Apache Software License
Platform: UNKNOWN
Requires-Dist: spaceone-core
Requires-Dist: spaceone-api
Requires-Dist: docker
Requires-Dist: kubernetes
Requires-Dist: redis
Requires-Dist: python-consul
Requires-Dist: hashids
